group_and_iter_everything/README.MD
group_and_iter_everything/__init__.py
group_and_iter_everything/requirements.txt
group_and_iter_everything/thirdparty.json
group_and_iter_everything-0.19.dist-info/LICENSE.rst
group_and_iter_everything-0.19.dist-info/METADATA
group_and_iter_everything-0.19.dist-info/WHEEL
group_and_iter_everything-0.19.dist-info/top_level.txt
group_and_iter_everything-0.19.dist-info/RECORD
