Metadata-Version: 2.1
Name: group-and-iter-everything
Version: 0.19
Summary: Many useful groupby / itertools functions
Home-page: https://github.com/hansalemaos/group_and_iter_everything
Author: Johannes Fischer
Author-email: <aulasparticularesdealemaosp@gmail.com>
License: MIT
Keywords: itertools,groupby
Classifier: Development Status :: 4 - Beta
Classifier: Programming Language :: Python :: 3 :: Only
Classifier: Programming Language :: Python :: 3.9
Classifier: Topic :: Scientific/Engineering :: Visualization
Classifier: Topic :: Software Development :: Libraries :: Python Modules
Classifier: Topic :: Text Editors :: Text Processing
Classifier: Topic :: Text Processing :: General
Classifier: Topic :: Text Processing :: Indexing
Classifier: Topic :: Text Processing :: Filters
Classifier: Topic :: Utilities
License-File: LICENSE.rst
Requires-Dist: check-if-nan
Requires-Dist: ctypes-window-info
Requires-Dist: dict-merger-keep-all
Requires-Dist: divide-region-into-rectangles
Requires-Dist: flatten-any-dict-iterable-or-whatsoever
Requires-Dist: flatten-everything
Requires-Dist: flexible-partial
Requires-Dist: get-consecutive-filename
Requires-Dist: hexintcalc
Requires-Dist: intersection-grouper
Requires-Dist: isiter
Requires-Dist: kthread-sleep
Requires-Dist: locate-pixelcolor
Requires-Dist: nestednop
Requires-Dist: numexpr
Requires-Dist: numpy
Requires-Dist: rect-intersection
Requires-Dist: regex
Requires-Dist: threadingbatch
Requires-Dist: tolerant-isinstance
Requires-Dist: xxhash
